odoo/addons/hr_recruitment_phone/__init__.py
odoo/addons/hr_recruitment_phone/__manifest__.py
odoo/addons/hr_recruitment_phone/i18n/es.po
odoo/addons/hr_recruitment_phone/i18n/hr_recruitment_phone.pot
odoo/addons/hr_recruitment_phone/i18n/tr.po
odoo/addons/hr_recruitment_phone/models/__init__.py
odoo/addons/hr_recruitment_phone/models/hr_applicant.py
odoo/addons/hr_recruitment_phone/security/ir.model.access.csv
odoo/addons/hr_recruitment_phone/static/description/icon.png
odoo/addons/hr_recruitment_phone/views/hr_applicant.xml
odoo11_addon_hr_recruitment_phone-11.0.1.0.0.99.dev3.dist-info/METADATA
odoo11_addon_hr_recruitment_phone-11.0.1.0.0.99.dev3.dist-info/RECORD
odoo11_addon_hr_recruitment_phone-11.0.1.0.0.99.dev3.dist-info/WHEEL
odoo11_addon_hr_recruitment_phone-11.0.1.0.0.99.dev3.dist-info/top_level.txt
